query_chain/__init__.py
query_chain/chain.py
query_chain/prompt.py
query_chain/query.py
query_chain-1.0.0.dist-info/METADATA
query_chain-1.0.0.dist-info/WHEEL
query_chain-1.0.0.dist-info/top_level.txt
query_chain-1.0.0.dist-info/RECORD
