Metadata-Version: 2.1
Name: query-chain
Version: 1.0.0
Summary: Query Chain
Home-page: https://github.itu.dk/pedf/academic-podcaster/tree/master/query_chain
Author: Pedro Ferreira
Author-email: i@pedropaf.com
